sunscan/__init__.py
sunscan/examples.py
sunscan/fit_utils.py
sunscan/fit_utils_extended.py
sunscan/math_utils.py
sunscan/params.py
sunscan/plotting.py
sunscan/scanner.py
sunscan/scanner_animation_streamlit.py
sunscan/scanner_estimation.py
sunscan/signal_simulation.py
sunscan/sun.py
sunscan/utils.py
sunscan/examples/sunscan1.nc
sunscan/examples/test1.nc
sunscanpy-0.1.3.dist-info/licenses/LICENSE
sunscanpy-0.1.3.dist-info/METADATA
sunscanpy-0.1.3.dist-info/WHEEL
sunscanpy-0.1.3.dist-info/top_level.txt
sunscanpy-0.1.3.dist-info/RECORD
