Metadata-Version: 2.4
Name: sunscanpy
Version: 0.1.3
Summary: A python module for radar pointing calibration using the sun
Author-email: Paul Ockenfuß <paul.ockenfuss@physik.uni-muenchen.de>, Gregor Köcher <gregor.koecher@physik.uni-muenchen.de>
License: CC-BY-SA-4.0
Project-URL: Homepage, https://github.com/Ockenfuss/sunscanpy
Keywords: radar,calibration,sun,atmosphere,doppler,cloud,weather
Classifier: Programming Language :: Python
Classifier: Programming Language :: Python :: 3
Classifier: Intended Audience :: Science/Research
Classifier: Topic :: Scientific/Engineering :: Atmospheric Science
Requires-Python: >=3.8
License-File: LICENSE
Requires-Dist: numpy>=1.20
Requires-Dist: xarray[accel]
Requires-Dist: matplotlib
Requires-Dist: pandas
Requires-Dist: scipy
Requires-Dist: skyfield>=1.40
Requires-Dist: ikpy
Requires-Dist: pyyaml
Provides-Extra: dev
Requires-Dist: pytest>=8.0; extra == "dev"
Requires-Dist: jupyter; extra == "dev"
Requires-Dist: streamlit; extra == "dev"
Dynamic: license-file
